decipyx/__init__.py
decipyx/data_handling.py
decipyx/estilos.py
decipyx/gui_automation.py
decipyx/os_automation.py
decipyx/testelib.py
decipyx/testing.py
decipyx/web_automation.py
decipyx/web_automation_roberto.py
decipyxlib/__init__.py
decipyxlib/data_handling.py
decipyxlib/estilos.py
decipyxlib/gui_automation.py
decipyxlib/os_automation.py
decipyxlib/testelib.py
decipyxlib/testing.py
decipyxlib/web_automation.py
decipyxlib/web_automation_roberto.py
decipyx-2.3.1.dist-info/METADATA
decipyx-2.3.1.dist-info/WHEEL
decipyx-2.3.1.dist-info/top_level.txt
decipyx-2.3.1.dist-info/RECORD
