Metadata-Version: 2.1
Name: decipyx
Version: 2.3.1
Summary: Uma biblioteca Python abrangente que oferece módulos para automação web, criação de GUI, tratamento de dados, testes e segue estritamente as diretrizes da PEP 8.
Author: Andrey Ruben Ribeiro Bessa
Author-email: andrey.bessa@gestao.gov.br
